MANIFEST.in
README.rst
setup.py
django_observer.egg-info/PKG-INFO
django_observer.egg-info/SOURCES.txt
django_observer.egg-info/dependency_links.txt
django_observer.egg-info/requires.txt
django_observer.egg-info/top_level.txt
django_observer.egg-info/zip-safe
observer/__init__.py
observer/mixins/__init__.py
observer/mixins/base.py
observer/mixins/callbacks.py
observer/mixins/models.py
observer/watchers/__init__.py
observer/watchers/base.py
observer/watchers/complex.py
observer/watchers/model.py
observer/watchers/relation.py
observer/watchers/value.py