Metadata-Version: 1.1
Name: django-observer
Version: 0.4.3
Summary: Watch any object/field/relation/generic relation of django and recive signals
Home-page: https://github.com/lambdalisue/django-observer
Author: Alisue
Author-email: lambdalisue@hashnote.net
License: MIT
Download-URL: https://github.com/lambdalisue/django-observer/tarball/master
Keywords: django signals object field relation generic
Platform: UNKNOWN
Classifier: Framework :: Django
Classifier: Intended Audience :: Developers
Classifier: License :: OSI Approved :: MIT License
Classifier: Programming Language :: Python
Classifier: Topic :: Internet :: WWW/HTTP
